aicsfeature/__init__.py
aicsfeature/kitchen_sink.py
aicsfeature/version.py
aicsfeature/bin/__init__.py
aicsfeature/extractor/__init__.py
aicsfeature/extractor/cell.py
aicsfeature/extractor/cell_nuc.py
aicsfeature/extractor/common.py
aicsfeature/extractor/dna.py
aicsfeature/extractor/fov.py
aicsfeature/extractor/structure.py
aicsfeature-0.2.1.dist-info/LICENSE.txt
aicsfeature-0.2.1.dist-info/METADATA
aicsfeature-0.2.1.dist-info/WHEEL
aicsfeature-0.2.1.dist-info/entry_points.txt
aicsfeature-0.2.1.dist-info/top_level.txt
aicsfeature-0.2.1.dist-info/RECORD
