Metadata-Version: 2.1
Name: aicsfeature
Version: 0.2.1
Summary: Scripts for image features calculation.
Home-page: UNKNOWN
Author: AICS
Author-email: jianxuc@alleninstitute.org
License: Allen Institute Software License
Platform: UNKNOWN
Requires-Dist: numpy
Requires-Dist: scipy
Requires-Dist: pandas
Requires-Dist: aicsimageprocessing
Requires-Dist: scikit-image (>=0.13.1)
Requires-Dist: matplotlib (>=2.0.0)
Requires-Dist: jupyter
Requires-Dist: mahotas
Requires-Dist: h5py
Provides-Extra: all
Requires-Dist: pytest ; extra == 'all'
Requires-Dist: pytest-cov ; extra == 'all'
Requires-Dist: flake8 ; extra == 'all'
Provides-Extra: interactive_dev_group
Provides-Extra: lint_group
Requires-Dist: flake8 ; extra == 'lint_group'
Provides-Extra: test_group
Requires-Dist: pytest ; extra == 'test_group'
Requires-Dist: pytest-cov ; extra == 'test_group'
